{"teams": ["Arsenal FC", "Aston Villa", "Blackburn Rovers", "Chelsea FC", "Coventry City", "Crystal Palace", "Everton FC", "Ipswich Town", "Leeds United", "Liverpool FC", "Manchester City", "Manchester United", "Norwich City", "Nottingham Forest", "Oldham Athletic", "Queens Park Rangers", "Sheffield United", "Sheffield Wednesday", "Southampton FC", "Tottenham Hotspur", "Milton Keynes Dons", "Middlesbrough FC", "Swindon Town", "Newcastle United", "West Ham United", "Leicester City", "Bolton Wanderers", "Derby County", "Sunderland AFC", "Barnsley FC", "Charlton Athletic", "Bradford City", "Watford FC", "Fulham FC", "West Bromwich Albion", "Birmingham City", "Portsmouth FC", "Wolverhampton Wanderers", "Wigan Athletic", "Reading FC", "Stoke City", "Hull City", "Burnley FC", "Blackpool FC", "Swansea City", "Cardiff City"], "meta": {"Arsenal FC":{"abbr":"ARS","color":"#FF0000"},"Aston Villa":{"abbr":"AST","color":"#84092E"},"Blackburn Rovers":{"abbr":"BLB","color":"#0066CC"},"Chelsea FC":{"abbr":"CHL","color":"#0000FF"},"Coventry City":{"abbr":"COV","color":"#75B2DD"},"Crystal Palace":{"abbr":"CRP","color":"#4267DC"},"Everton FC":{"abbr":"EVE","color":"#1D18F5"},"Ipswich Town":{"abbr":"IPS","color":"#0000EE"},"Leeds United":{"abbr":"LDS","color":"#00A2E8"},"Liverpool FC":{"abbr":"LIV","color":"#FF0000"},"Manchester City":{"abbr":"MCY","color":"#5EBFF4"},"Manchester United":{"abbr":"MUN","color":"#E20E0E"},"Norwich City":{"abbr":"NOR","color":"#009933"},"Nottingham Forest":{"abbr":"NOT","color":"#696969"},"Oldham Athletic":{"abbr":"OLD","color":"#000080"},"Queens Park Rangers":{"abbr":"QPR","color":"#316654"},"Sheffield United":{"abbr":"SHU","color":"#FFFF00"},"Sheffield Wednesday":{"abbr":"SHW","color":"#0000CD"},"Southampton FC":{"abbr":"SOU","color":"#FF0000"},"Tottenham Hotspur":{"abbr":"TOT","color":"#4AB1E0"},"Milton Keynes Dons":{"abbr":"MIL","color":"#FF0000"},"Middlesbrough FC":{"abbr":"MID","color":"#FF0000"},"Swindon Town":{"abbr":"SWI","color":"#FF0000"},"Newcastle United":{"abbr":"NEW","color":"#12173D"},"West Ham United":{"abbr":"WHU","color":"#80BFFF"},"Leicester City":{"abbr":"LEC","color":"#0033CC"},"Bolton Wanderers":{"abbr":"BOL","color":"#032269"},"Derby County":{"abbr":"DER","color":"#990033"},"Sunderland AFC":{"abbr":"SUN","color":"#FFFF00"},"Barnsley FC":{"abbr":"BRN","color":"#FF0000"},"Charlton Athletic":{"abbr":"CHA","color":"#FF0000"},"Bradford City":{"abbr":"BRA","color":"#FFCC00"},"Watford FC":{"abbr":"WAT","color":"#6D242D"},"Fulham FC":{"abbr":"FUL","color":"#013876"},"West Bromwich Albion":{"abbr":"WBA","color":"#FF0000"},"Birmingham City":{"abbr":"BIR","color":"#004FA6"},"Portsmouth FC":{"abbr":"POR","color":"#0000BF"},"Wolverhampton Wanderers":{"abbr":"WOL","color":"#FF8000"},"Wigan Athletic":{"abbr":"WIG","color":"#236BD8"},"Reading FC":{"abbr":"REA","color":"#FFDF00"},"Stoke City":{"abbr":"STC","color":"#FF0000"},"Hull City":{"abbr":"HCY","color":"#FAA61A"},"Burnley FC":{"abbr":"BUR","color":"#7F0000"},"Blackpool FC":{"abbr":"BLP","color":"#F68712"},"Swansea City":{"abbr":"SWC","color":"#2D017E"},"Cardiff City":{"abbr":"CAR","color":"#FEFE53"}}}